{
  "family": "smartdhobi-backend-task",
  "networkMode": "awsvpc",
  "requiresCompatibilities": ["FARGATE"],
  "cpu": "256",
  "memory": "512",
  "executionRoleArn": "arn:aws:iam::ACCOUNT_ID:role/smartdhobi-ecs-task-execution-role",
  "containerDefinitions": [
    {
      "name": "smartdhobi-backend",
      "image": "ACCOUNT_ID.dkr.ecr.ap-south-1.amazonaws.com/smartdhobi-backend:latest",
      "portMappings": [
        {
          "containerPort": 1200,
          "protocol": "tcp"
        }
      ],
      "essential": true,
      "environment": [
        {
          "name": "PORT",
          "value": "1200"
        },
        {
          "name": "NODE_ENV",
          "value": "production"
        }
      ],
      "secrets": [
        {
          "name": "MONGODB_URL",
          "valueFrom": "arn:aws:secretsmanager:ap-south-1:ACCOUNT_ID:secret:smartdhobi/mongodb-url"
        },
        {
          "name": "JWT_SECRET",
          "valueFrom": "arn:aws:secretsmanager:ap-south-1:ACCOUNT_ID:secret:smartdhobi/jwt-secret"
        },
        {
          "name": "EMAIL_USERNAME",
          "valueFrom": "arn:aws:secretsmanager:ap-south-1:ACCOUNT_ID:secret:smartdhobi/email-username"
        },
        {
          "name": "EMAIL_PASSWORD",
          "valueFrom": "arn:aws:secretsmanager:ap-south-1:ACCOUNT_ID:secret:smartdhobi/email-password"
        },
        {
          "name": "CLOUD_NAME",
          "valueFrom": "arn:aws:secretsmanager:ap-south-1:ACCOUNT_ID:secret:smartdhobi/cloudinary-name"
        },
        {
          "name": "API_KEY",
          "valueFrom": "arn:aws:secretsmanager:ap-south-1:ACCOUNT_ID:secret:smartdhobi/cloudinary-key"
        },
        {
          "name": "API_SECRET",
          "valueFrom": "arn:aws:secretsmanager:ap-south-1:ACCOUNT_ID:secret:smartdhobi/cloudinary-secret"
        },
        {
          "name": "RAZORPAY_KEY_ID",
          "valueFrom": "arn:aws:secretsmanager:ap-south-1:ACCOUNT_ID:secret:smartdhobi/razorpay-key-id"
        },
        {
          "name": "RAZORPAY_KEY_SECRET",
          "valueFrom": "arn:aws:secretsmanager:ap-south-1:ACCOUNT_ID:secret:smartdhobi/razorpay-key-secret"
        }
      ],
      "logConfiguration": {
        "logDriver": "awslogs",
        "options": {
          "awslogs-group": "/ecs/smartdhobi-backend",
          "awslogs-region": "ap-south-1",
          "awslogs-stream-prefix": "ecs"
        }
      }
    }
  ]
}